lollopackagename/__init__.py
lollopackagename/hello.py
lollosayhello-0.0.2.dist-info/METADATA
lollosayhello-0.0.2.dist-info/WHEEL
lollosayhello-0.0.2.dist-info/top_level.txt
lollosayhello-0.0.2.dist-info/RECORD
