Metadata-Version: 2.1
Name: lollosayhello
Version: 0.0.2
Summary: im testing a basic sayhello thingy
Author: Lollino (Lorenzo Mogicato)
Author-email: <lorenzo.mogicato@gmail.com>
License: UNKNOWN
Keywords: lollino
Platform: UNKNOWN
Classifier: Development Status :: 1 - Planning
Classifier: Programming Language :: Python :: 3
Classifier: Operating System :: Unix
Classifier: Operating System :: MacOS :: MacOS X
Classifier: Operating System :: Microsoft :: Windows
